{
  "Version": 3,
  "Meta": {
    "Duration": 14.07,
    "Fps": 30.0,
    "Loop": true,
    "AreBeziersRestricted": true,
    "CurveCount": 132,
    "TotalSegmentCount": 1046,
    "TotalPointCount": 1594,
    "UserDataCount": 1,
    "TotalUserDataSize": 0
  },
  "Curves": [
    {
      "Target": "Parameter",
      "Id": "ParamEyeLOpen",
      "Segments": [
        0,
        1,
        2,
        0.667,
        1,
        0,
        0.833,
        0,
        0,
        1,
        1,
        2,
        2.6,
        1,
        0,
        2.767,
        0,
        1,
        2.822,
        0,
        2.878,
        0.925,
        2.933,
        1,
        1,
        3.222,
        1.39,
        3.511,
        1.5,
        3.8,
        1.5,
        1,
        4.344,
        1.5,
        4.889,
        1.499,
        5.433,
        1.466,
        1,
        6.311,
        1.413,
        7.189,
        1.326,
        8.067,
        1.243,
        1,
        8.167,
        1.234,
        8.267,
        0,
        8.367,
        0,
        2,
        8.933,
        0,
        0,
        9.533,
        1,
        2,
        11.2,
        1,
        1,
        11.422,
        1,
        11.645,
        0.865,
        11.867,
        0.8,
        1,
        12.178,
        0.709,
        12.489,
        0.7,
        12.8,
        0.7,
        0,
        13.367,
        1,
        2,
        14.067,
        1
      ]
    },
    {
      "Target": "Parameter",
      "Id": "ParamEyeROpen",
      "Segments": [
        0,
        1,
        2,
        0.667,
        1,
        0,
        0.833,
        0,
        0,
        1,
        1,
        2,
        2.6,
        1,
        0,
        2.767,
        0,
        1,
        2.822,
        0,
        2.878,
        0.925,
        2.933,
        1,
        1,
        3.222,
        1.39,
        3.511,
        1.5,
        3.8,
        1.5,
        1,
        4.344,
        1.5,
        4.889,
        1.5,
        5.433,
        1.466,
        1,
        6.211,
        1.395,
        6.989,
        0.8,
        7.767,
        0.8,
        0,
        8.067,
        0.803,
        0,
        8.367,
        0,
        2,
        8.933,
        0,
        0,
        9.533,
        1,
        2,
        11.2,
        1,
        0,
        11.833,
        0,
        2,
        12.8,
        0,
        0,
        13.367,
        1,
        2,
        14.067,
        1
      ]
    },
    {
      "Target": "Parameter",
      "Id": "ParamEyeRSmile",
      "Segments": [
        0,
        1,
        0,
        7.767,
        0,
        1,
        7.867,
        0,
        7.967,
        0,
        8.067,
        0.014,
        1,
        8.167,
        0.032,
        8.267,
        1,
        8.367,
        1,
        2,
        14.067,
        1
      ]
    },
    {
      "Target": "Parameter",
      "Id": "ParamEyeBallX",
      "Segments": [
        0,
        1,
        2,
        5.367,
        1,
        1,
        6.211,
        1,
        7.056,
        0.764,
        7.9,
        0.2,
        1,
        8.344,
        -0.097,
        8.789,
        -0.569,
        9.233,
        -0.8,
        1,
        9.589,
        -0.985,
        9.944,
        -1,
        10.3,
        -1,
        1,
        10.556,
        -1,
        10.811,
        0.758,
        11.067,
        0.8,
        1,
        12.067,
        0.966,
        13.067,
        1,
        14.067,
        1
      ]
    },
    {
      "Target": "Parameter",
      "Id": "ParamEYET",
      "Segments": [
        0,
        0,
        0,
        1.467,
        0.5,
        0,
        2.733,
        0.486,
        0,
        3.767,
        1,
        1,
        4.389,
        1,
        5.011,
        1,
        5.633,
        0.913,
        1,
        6.211,
        0.821,
        6.789,
        0.27,
        7.367,
        -0.2,
        1,
        7.778,
        -0.534,
        8.189,
        -1,
        8.6,
        -1,
        0,
        14.067,
        0
      ]
    },
    {
      "Target": "Parameter",
      "Id": "ParamParamBrowLY",
      "Segments": [
        0,
        0,
        0,
        2.033,
        0.7,
        0,
        2.467,
        0,
        0,
        4.167,
        1,
        0,
        5.2,
        0,
        2,
        7.667,
        0,
        2,
        14.067,
        0
      ]
    },
    {
      "Target": "Parameter",
      "Id": "ParamParamBrowRY",
      "Segments": [
        0,
        0,
        0,
        2.033,
        0.4,
        1,
        2.178,
        0.4,
        2.322,
        0.027,
        2.467,
        0,
        1,
        4.2,
        -0.322,
        5.934,
        -0.782,
        7.667,
        -0.9,
        1,
        9.278,
        -1,
        10.889,
        -1,
        12.5,
        -1,
        0,
        14.067,
        0
      ]
    },
    {
      "Target": "Parameter",
      "Id": "ParamBrowLAngle",
      "Segments": [
        0,
        0,
        2,
        1.1,
        0,
        0,
        1.8,
        -0.3,
        0,
        2.533,
        0,
        0,
        7.667,
        -0.5,
        0,
        8.9,
        0,
        2,
        14.067,
        0
      ]
    },
    {
      "Target": "Parameter",
      "Id": "ParamBrowRAngle",
      "Segments": [
        0,
        0,
        2,
        1.1,
        0,
        2,
        2.533,
        0,
        0,
        7.667,
        -0.4,
        0,
        8.9,
        0,
        2,
        14.067,
        0
      ]
    },
    {
      "Target": "Parameter",
      "Id": "ParamBrowLForm",
      "Segments": [
        0,
        0,
        2,
        1.1,
        0,
        0,
        1.8,
        -1,
        0,
        2.533,
        0,
        1,
        3.078,
        0,
        3.622,
        -0.306,
        4.167,
        -0.7,
        1,
        4.511,
        -0.949,
        4.856,
        -1,
        5.2,
        -1,
        0,
        7.7,
        -0.806,
        0,
        12.5,
        -1,
        0,
        14.067,
        0
      ]
    },
    {
      "Target": "Parameter",
      "Id": "ParamBrowRForm",
      "Segments": [
        0,
        0,
        2,
        1.1,
        0,
        0,
        1.8,
        1,
        1,
        2.044,
        1,
        2.289,
        0.217,
        2.533,
        0,
        1,
        3.422,
        -0.79,
        4.311,
        -1,
        5.2,
        -1,
        1,
        6.022,
        -1,
        6.845,
        -0.989,
        7.667,
        -0.811,
        1,
        8.078,
        -0.722,
        8.489,
        0.612,
        8.9,
        0.7,
        1,
        10.1,
        0.957,
        11.3,
        1,
        12.5,
        1,
        0,
        14.067,
        0
      ]
    },
    {
      "Target": "Parameter",
      "Id": "ParamMouthForm",
      "Segments": [
        0,
        0,
        0,
        0.267,
        -0.4,
        0,
        0.5,
        0.4,
        0,
        0.767,
        -0.4,
        1,
        0.867,
        -0.4,
        0.967,
        -0.389,
        1.067,
        -0.1,
        1,
        1.145,
        0.125,
        1.222,
        0.7,
        1.3,
        0.7,
        0,
        1.667,
        -0.3,
        1,
        1.856,
        -0.3,
        2.044,
        -0.3,
        2.233,
        -0.298,
        1,
        2.3,
        -0.297,
        2.366,
        -0.153,
        2.433,
        0,
        1,
        2.511,
        0.179,
        2.589,
        0.5,
        2.667,
        0.5,
        0,
        2.867,
        -0.4,
        0,
        3.067,
        0.1,
        1,
        3.167,
        0.1,
        3.267,
        -0.368,
        3.367,
        -0.5,
        1,
        3.456,
        -0.617,
        3.544,
        -0.6,
        3.633,
        -0.6,
        0,
        3.867,
        0,
        1,
        4.022,
        0,
        4.178,
        -0.01,
        4.333,
        -0.1,
        1,
        4.478,
        -0.183,
        4.622,
        -0.3,
        4.767,
        -0.3,
        0,
        5.233,
        0.4,
        0,
        5.7,
        -0.4,
        0,
        6.367,
        0.5,
        0,
        6.767,
        -0.4,
        0,
        7.333,
        0.5,
        0,
        7.867,
        0.2,
        0,
        8.067,
        1,
        2,
        8.167,
        1,
        0,
        8.433,
        0.9,
        0,
        9.167,
        1,
        0,
        9.367,
        0.2,
        0,
        9.7,
        0.8,
        0,
        9.933,
        -0.3,
        0,
        10.333,
        0.3,
        0,
        10.567,
        -0.1,
        1,
        11.245,
        -0.1,
        11.922,
        0.254,
        12.6,
        0.7,
        1,
        12.989,
        0.956,
        13.378,
        0.999,
        13.767,
        0.999,
        1,
        13.811,
        0.999,
        13.856,
        0.365,
        13.9,
        0.2,
        1,
        13.956,
        -0.006,
        14.011,
        0,
        14.067,
        0
      ]
    },
    {
      "Target": "Parameter",
      "Id": "ParamMouthOpenY",
      "Segments": [
        0,
        0,
        0,
        0.067,
        0.773,
        0,
        0.133,
        0.306,
        0,
        0.2,
        0.69,
        0,
        0.267,
        0.318,
        0,
        0.333,
        0.361,
        0,
        0.4,
        0.231,
        0,
        0.467,
        0.314,
        0,
        0.533,
        0.286,
        0,
        0.667,
        0.631,
        0,
        0.8,
        0.106,
        0,
        0.867,
        0.569,
        0,
        0.933,
        0.133,
        0,
        1.067,
        0.89,
        0,
        1.267,
        0.082,
        0,
        1.333,
        0.537,
        1,
        1.4,
        0.537,
        1.466,
        0.484,
        1.533,
        0.271,
        1,
        1.566,
        0.164,
        1.6,
        0,
        1.633,
        0,
        2,
        2.333,
        0,
        0,
        2.4,
        0.404,
        0,
        2.467,
        0.047,
        0,
        2.533,
        0.89,
        0,
        2.6,
        0.435,
        0,
        2.8,
        0.871,
        0,
        3,
        0.055,
        0,
        3.067,
        0.49,
        0,
        3.133,
        0.071,
        0,
        3.267,
        0.898,
        0,
        3.333,
        0.624,
        0,
        3.467,
        0.667,
        0,
        3.667,
        0.082,
        0,
        3.8,
        0.725,
        0,
        3.933,
        0.376,
        0,
        4,
        0.463,
        0,
        4.067,
        0.02,
        0,
        4.2,
        0.855,
        0,
        4.267,
        0.329,
        0,
        4.333,
        0.871,
        0,
        4.4,
        0.184,
        0,
        4.533,
        0.545,
        1,
        4.6,
        0.545,
        4.666,
        0.307,
        4.733,
        0.129,
        1,
        4.755,
        0.07,
        4.778,
        0.086,
        4.8,
        0.086,
        0,
        4.867,
        0.698,
        0,
        5,
        0.055,
        0,
        5.067,
        0.145,
        0,
        5.133,
        0,
        2,
        5.7,
        0,
        0,
        5.8,
        0.478,
        0,
        5.867,
        0.004,
        0,
        5.933,
        0.784,
        0,
        6,
        0.471,
        0,
        6.133,
        0.89,
        0,
        6.2,
        0.02,
        0,
        6.267,
        0.486,
        0,
        6.333,
        0.255,
        0,
        6.4,
        0.839,
        2,
        6.467,
        0.839,
        0,
        6.533,
        0.451,
        0,
        6.667,
        0.678,
        0,
        6.8,
        0.169,
        0,
        6.867,
        0.294,
        0,
        6.933,
        0.208,
        1,
        6.955,
        0.208,
        6.978,
        0.483,
        7,
        0.514,
        1,
        7.044,
        0.577,
        7.089,
        0.58,
        7.133,
        0.58,
        0,
        7.233,
        0,
        2,
        7.9,
        0,
        0,
        8.067,
        0.639,
        0,
        8.233,
        0,
        0,
        9.267,
        0.816,
        0,
        9.333,
        0.463,
        0,
        9.4,
        0.58,
        0,
        9.467,
        0.059,
        0,
        9.533,
        0.918,
        0,
        9.6,
        0.145,
        0,
        9.733,
        0.831,
        0,
        9.867,
        0.18,
        0,
        10,
        0.902,
        0,
        10.2,
        0.545,
        0,
        10.267,
        0.965,
        0,
        10.467,
        0.325,
        0,
        10.533,
        0.4,
        0,
        10.6,
        0,
        2,
        11.267,
        0,
        0,
        11.4,
        0.588,
        0,
        11.467,
        0.067,
        0,
        11.533,
        0.98,
        0,
        11.6,
        0.541,
        0,
        11.667,
        0.988,
        0,
        11.733,
        0.008,
        0,
        12,
        0.929,
        0,
        12.2,
        0.129,
        1,
        12.267,
        0.129,
        12.333,
        0.557,
        12.4,
        0.655,
        1,
        12.533,
        0.851,
        12.667,
        0.871,
        12.8,
        0.871,
        0,
        12.933,
        0.518,
        1,
        12.955,
        0.518,
        12.978,
        0.89,
        13,
        0.894,
        1,
        13.044,
        0.902,
        13.089,
        0.902,
        13.133,
        0.902,
        0,
        13.2,
        0.482,
        0,
        13.267,
        0.776,
        0,
        13.533,
        0.22,
        0,
        13.667,
        0.431,
        0,
        13.8,
        0.145,
        0,
        13.867,
        0.18,
        0,
        14.067,
        0
      ]
    },
    {
      "Target": "Parameter",
      "Id": "ParamArmL",
      "Segments": [
        0,
        0,
        0,
        1.467,
        -15,
        2,
        2.4,
        -15,
        0,
        4.467,
        -9,
        1,
        4.889,
        -9,
        5.311,
        -9.198,
        5.733,
        -11,
        1,
        6.111,
        -12.612,
        6.489,
        -15,
        6.867,
        -15,
        2,
        7.7,
        -15,
        0,
        8.167,
        -30,
        2,
        9.333,
        -30,
        1,
        9.933,
        -30,
        10.533,
        -27.529,
        11.133,
        -24,
        1,
        11.533,
        -21.648,
        11.933,
        -20.239,
        12.333,
        -18,
        1,
        12.633,
        -16.32,
        12.933,
        -15.113,
        13.233,
        -12,
        1,
        13.511,
        -9.118,
        13.789,
        0,
        14.067,
        0
      ]
    },
    {
      "Target": "Parameter",
      "Id": "ParamArmL1",
      "Segments": [
        0,
        9.544,
        0,
        1.167,
        -30,
        1,
        1.478,
        -30,
        1.789,
        -30,
        2.1,
        -26.973,
        1,
        2.5,
        -21.897,
        2.9,
        30,
        3.3,
        30,
        0,
        6.067,
        26.642,
        0,
        6.867,
        30,
        2,
        7.7,
        30,
        0,
        8.167,
        -21,
        2,
        9.333,
        -21,
        1,
        9.611,
        -21,
        9.889,
        -8.117,
        10.167,
        -5,
        1,
        10.489,
        -1.384,
        10.811,
        -2.23,
        11.133,
        1.948,
        1,
        11.533,
        7.135,
        11.933,
        30,
        12.333,
        30,
        2,
        13.233,
        30,
        0,
        14.067,
        9.544
      ]
    },
    {
      "Target": "Parameter",
      "Id": "ParamArmL1Y",
      "Segments": [
        0,
        0,
        0,
        4.467,
        30,
        0,
        6.033,
        27.864,
        0,
        6.867,
        30,
        2,
        7.7,
        30,
        0,
        8.167,
        0,
        2,
        9.333,
        0,
        0,
        10.167,
        30,
        0,
        11.133,
        25.386,
        2,
        12.333,
        25.386,
        2,
        13.233,
        25.386,
        0,
        14.067,
        0
      ]
    },
    {
      "Target": "Parameter",
      "Id": "ParamHandL",
      "Segments": [
        0,
        -2.919,
        0,
        0.833,
        -30,
        0,
        1.2,
        -25,
        0,
        2.1,
        -30,
        0,
        4.467,
        30,
        0,
        6.867,
        -22,
        2,
        7.7,
        -22,
        0,
        8.167,
        -25,
        1,
        8.3,
        -25,
        8.434,
        -23.597,
        8.567,
        -22,
        1,
        8.7,
        -20.403,
        8.834,
        -20,
        8.967,
        -20,
        2,
        9.333,
        -20,
        0,
        10.167,
        1,
        0,
        11.133,
        -2.919,
        0,
        12.367,
        4.128,
        1,
        12.656,
        4.128,
        12.944,
        2.788,
        13.233,
        0.397,
        1,
        13.511,
        -1.902,
        13.789,
        -2.919,
        14.067,
        -2.919
      ]
    },
    {
      "Target": "Parameter",
      "Id": "ParamFingerL",
      "Segments": [
        0,
        -0.3,
        1,
        0.178,
        -0.3,
        0.355,
        -0.027,
        0.533,
        0.1,
        1,
        1.455,
        0.76,
        2.378,
        1,
        3.3,
        1,
        0,
        4.467,
        -0.8,
        1,
        5.022,
        -0.8,
        5.578,
        -0.796,
        6.133,
        -0.76,
        1,
        6.322,
        -0.748,
        6.511,
        1,
        6.7,
        1,
        2,
        7.833,
        1,
        0,
        8.167,
        -0.6,
        2,
        9.333,
        -0.6,
        0,
        11.133,
        1,
        2,
        12.333,
        1,
        2,
        13.233,
        1,
        0,
        14.067,
        -0.3
      ]
    },
    {
      "Target": "Parameter",
      "Id": "ParamArmR",
      "Segments": [
        0,
        0,
        1,
        0.422,
        0,
        0.845,
        -8.043,
        1.267,
        -16,
        1,
        1.667,
        -23.538,
        2.067,
        -25,
        2.467,
        -25,
        0,
        5.8,
        -19.993,
        0,
        7.433,
        -20,
        0,
        8.567,
        -10,
        0,
        13.233,
        -20,
        0,
        14.067,
        0
      ]
    },
    {
      "Target": "Parameter",
      "Id": "ParamArmRY",
      "Segments": [
        0,
        0,
        1,
        0.422,
        0,
        0.845,
        -18.347,
        1.267,
        -19,
        1,
        3.322,
        -22.179,
        5.378,
        -23,
        7.433,
        -23,
        2,
        13.233,
        -23,
        0,
        14.067,
        0
      ]
    },
    {
      "Target": "Parameter",
      "Id": "ParamArmR1",
      "Segments": [
        0,
        0.757,
        1,
        0.422,
        0.757,
        0.845,
        0.284,
        1.267,
        -3,
        1,
        1.667,
        -6.111,
        2.067,
        -10,
        2.467,
        -10,
        1,
        2.878,
        -10,
        3.289,
        -3.853,
        3.7,
        -3,
        1,
        4.4,
        -1.548,
        5.1,
        -1.525,
        5.8,
        -1.525,
        1,
        6.333,
        -1.525,
        6.867,
        -4.199,
        7.4,
        -9,
        1,
        7.789,
        -12.5,
        8.178,
        -14,
        8.567,
        -14,
        1,
        10.111,
        -14,
        11.656,
        -12.878,
        13.2,
        -9,
        1,
        13.489,
        -8.275,
        13.778,
        0.757,
        14.067,
        0.757
      ]
    },
    {
      "Target": "Parameter",
      "Id": "ParamArmR1Y",
      "Segments": [
        0,
        0,
        1,
        0.422,
        0,
        0.845,
        -14.548,
        1.267,
        -21,
        1,
        1.811,
        -29.319,
        2.356,
        -30,
        2.9,
        -30,
        2,
        7.433,
        -30,
        2,
        13.233,
        -30,
        0,
        14.067,
        0
      ]
    },
    {
      "Target": "Parameter",
      "Id": "ParamHandR",
      "Segments": [
        0,
        7.59,
        0,
        1.267,
        23,
        0,
        14.067,
        7.59
      ]
    },
    {
      "Target": "Parameter",
      "Id": "ParamFingerR",
      "Segments": [
        0,
        0.393,
        0,
        1.267,
        1,
        0,
        14.067,
        0.393
      ]
    },
    {
      "Target": "Parameter",
      "Id": "ParamLegL1",
      "Segments": [
        0,
        0,
        0,
        2,
        30,
        0,
        4,
        0,
        0,
        6,
        30,
        1,
        6.667,
        30,
        7.333,
        23.625,
        8,
        0,
        1,
        8.244,
        -8.663,
        8.489,
        -30,
        8.733,
        -30,
        2,
        12.233,
        -30,
        0,
        14.067,
        0
      ]
    },
    {
      "Target": "Parameter",
      "Id": "ParamLegL",
      "Segments": [
        0,
        0,
        0,
        2,
        12,
        0,
        4,
        -10,
        0,
        6,
        11,
        0,
        7.267,
        0,
        0,
        7.733,
        7,
        0,
        8.9,
        -30,
        0,
        14.067,
        0
      ]
    },
    {
      "Target": "Parameter",
      "Id": "ParamLegLY",
      "Segments": [
        0,
        0,
        0,
        2,
        30,
        0,
        4,
        0,
        0,
        6,
        30,
        0,
        8,
        0,
        0,
        10.133,
        30,
        0,
        14.067,
        0
      ]
    },
    {
      "Target": "Parameter",
      "Id": "ParamFootL",
      "Segments": [
        0,
        15,
        0,
        1,
        -30,
        0,
        3,
        30,
        0,
        5,
        -30,
        0,
        7,
        30,
        1,
        7.333,
        30,
        7.667,
        17.915,
        8,
        15,
        1,
        9.022,
        6.061,
        10.045,
        4,
        11.067,
        4,
        0,
        14.067,
        15
      ]
    },
    {
      "Target": "Parameter",
      "Id": "ParamLegR1",
      "Segments": [
        0,
        0.437,
        0,
        1.733,
        9,
        0,
        3.733,
        0,
        0,
        5.733,
        11,
        0,
        7.733,
        0,
        0,
        8,
        0.437,
        0,
        8.733,
        -30,
        2,
        12.233,
        -30,
        0,
        14.067,
        0.437
      ]
    },
    {
      "Target": "Parameter",
      "Id": "ParamLegR",
      "Segments": [
        0,
        0,
        0,
        2,
        8,
        0,
        4,
        0,
        0,
        6,
        12,
        0,
        7.267,
        0,
        0,
        7.733,
        5,
        0,
        8.9,
        -13,
        0,
        14.067,
        0
      ]
    },
    {
      "Target": "Parameter",
      "Id": "ParamLegRY",
      "Segments": [
        0,
        14,
        1,
        0.189,
        14,
        0.378,
        13.06,
        0.567,
        11,
        1,
        1.234,
        3.729,
        1.9,
        0,
        2.567,
        0,
        0,
        4.567,
        13,
        0,
        6.567,
        0,
        1,
        7.045,
        0,
        7.522,
        6.105,
        8,
        14,
        1,
        8.711,
        25.75,
        9.422,
        30,
        10.133,
        30,
        0,
        14.067,
        14
      ]
    },
    {
      "Target": "Parameter",
      "Id": "ParamFootR",
      "Segments": [
        0,
        -15,
        0,
        1,
        13,
        0,
        3,
        -30,
        0,
        5,
        9,
        0,
        7,
        -30,
        0,
        8,
        -15,
        0,
        11.067,
        -30,
        0,
        14.067,
        -15
      ]
    },
    {
      "Target": "Parameter",
      "Id": "ParamWave",
      "Segments": [
        0,
        0.5,
        0,
        1.367,
        0.2,
        0,
        6.767,
        0.5,
        0,
        8.467,
        0.1,
        0,
        14.067,
        0.5
      ]
    },
    {
      "Target": "Parameter",
      "Id": "ParamWATER",
      "Segments": [
        0,
        0.5,
        0,
        0.6,
        1,
        0,
        1.467,
        0,
        0,
        2.7,
        1,
        0,
        4.8,
        0.2,
        0,
        6.667,
        0.8,
        0,
        8.733,
        0.2,
        0,
        10.7,
        0.8,
        0,
        12.5,
        0.3,
        0,
        14.067,
        0.5
      ]
    },
    {
      "Target": "Parameter",
      "Id": "ParamOpaishakeX",
      "Segments": [
        0,
        0,
        0,
        1.133,
        -0.2,
        0,
        1.8,
        0.4,
        0,
        2.233,
        -0.1,
        0,
        2.967,
        0.2,
        0,
        3.633,
        -0.2,
        0,
        3.967,
        0.1,
        0,
        4.433,
        -0.001,
        2,
        4.467,
        -0.001,
        0,
        6,
        0,
        0,
        6.533,
        -0.2,
        0,
        7.033,
        0.2,
        0,
        7.367,
        -0.006,
        0,
        7.7,
        0.001,
        2,
        7.767,
        0.001,
        0,
        8.3,
        0.011,
        2,
        8.333,
        0.011,
        0,
        9,
        -0.027,
        0,
        9.567,
        0.012,
        0,
        9.933,
        0.003,
        2,
        9.967,
        0.003,
        2,
        10.033,
        0.003,
        2,
        10.067,
        0.003,
        2,
        10.1,
        0.003,
        2,
        10.133,
        0.003,
        2,
        10.167,
        0.003,
        2,
        10.267,
        0.003,
        2,
        10.467,
        0.003,
        2,
        10.533,
        0.003,
        2,
        10.6,
        0.003,
        2,
        10.633,
        0.003,
        0,
        10.667,
        0.002,
        2,
        10.767,
        0.002,
        2,
        10.8,
        0.002,
        2,
        10.833,
        0.002,
        2,
        10.867,
        0.002,
        2,
        10.967,
        0.002,
        2,
        11,
        0.002,
        2,
        11.033,
        0.002,
        2,
        11.067,
        0.002,
        2,
        11.133,
        0.002,
        2,
        11.167,
        0.002,
        2,
        11.233,
        0.002,
        2,
        11.267,
        0.002,
        2,
        11.367,
        0.002,
        2,
        11.4,
        0.002,
        0,
        12.567,
        0.2,
        0,
        13.133,
        0.028,
        0,
        13.167,
        0.029,
        0,
        14.067,
        0
      ]
    },
    {
      "Target": "Parameter",
      "Id": "ParamOpaishakeY",
      "Segments": [
        0,
        0,
        0,
        0.333,
        0.4,
        0,
        1.167,
        -0.6,
        0,
        1.733,
        0.2,
        0,
        2,
        -0.1,
        0,
        2.2,
        -0.003,
        0,
        2.633,
        -0.023,
        2,
        2.667,
        -0.023,
        0,
        2.933,
        -0.015,
        0,
        2.967,
        -0.016,
        2,
        3,
        -0.016,
        0,
        3.033,
        -0.017,
        2,
        3.067,
        -0.017,
        2,
        3.1,
        -0.017,
        0,
        3.133,
        -0.016,
        0,
        3.167,
        -0.017,
        0,
        3.567,
        -0.01,
        2,
        3.633,
        -0.01,
        0,
        3.967,
        0.037,
        0,
        4.233,
        0.018,
        0,
        4.5,
        0.024,
        0,
        4.533,
        0.023,
        2,
        4.567,
        0.023,
        2,
        4.733,
        0.023,
        2,
        4.767,
        0.023,
        2,
        4.8,
        0.023,
        2,
        4.833,
        0.023,
        2,
        4.867,
        0.023,
        0,
        4.9,
        0.022,
        2,
        4.933,
        0.022,
        2,
        4.967,
        0.022,
        2,
        5,
        0.022,
        2,
        5.033,
        0.022,
        2,
        5.067,
        0.022,
        0,
        5.633,
        0.018,
        0,
        5.7,
        0.022,
        2,
        5.733,
        0.022,
        0,
        6.3,
        -0.043,
        0,
        6.367,
        -0.041,
        2,
        6.4,
        -0.041,
        2,
        6.433,
        -0.041,
        2,
        6.467,
        -0.041,
        2,
        6.5,
        -0.041,
        2,
        6.533,
        -0.041,
        2,
        6.567,
        -0.041,
        0,
        7.067,
        0.009,
        0,
        7.333,
        -0.015,
        1,
        7.466,
        -0.015,
        7.6,
        -0.021,
        7.733,
        0,
        1,
        7.889,
        0.025,
        8.044,
        0.6,
        8.2,
        0.6,
        0,
        8.933,
        -0.5,
        0,
        9.533,
        0.3,
        0,
        9.767,
        -0.006,
        0,
        10.433,
        0.015,
        2,
        10.467,
        0.015,
        2,
        10.5,
        0.015,
        2,
        10.567,
        0.015,
        0,
        10.7,
        0.014,
        2,
        10.733,
        0.014,
        0,
        11.833,
        -0.067,
        2,
        11.867,
        -0.067,
        0,
        11.9,
        -0.068,
        0,
        11.933,
        -0.067,
        2,
        11.967,
        -0.067,
        0,
        13.2,
        0.057,
        2,
        13.233,
        0.057,
        0,
        13.3,
        0.058,
        0,
        14.067,
        0
      ]
    },
    {
      "Target": "Parameter",
      "Id": "ParamOpaishakeX2",
      "Segments": [
        0,
        0,
        0,
        1.133,
        -0.2,
        0,
        1.8,
        0.4,
        0,
        2.233,
        -0.1,
        0,
        2.967,
        0.2,
        0,
        3.633,
        -0.2,
        0,
        3.967,
        0.1,
        0,
        4.433,
        -0.001,
        2,
        4.467,
        -0.001,
        0,
        6,
        0,
        0,
        6.533,
        -0.2,
        0,
        7.033,
        0.3,
        0,
        7.367,
        -0.006,
        0,
        7.7,
        0.001,
        2,
        7.767,
        0.001,
        0,
        8.3,
        0.011,
        2,
        8.333,
        0.011,
        0,
        9,
        -0.027,
        0,
        9.567,
        0.012,
        0,
        9.933,
        0.003,
        2,
        9.967,
        0.003,
        2,
        10.033,
        0.003,
        2,
        10.067,
        0.003,
        2,
        10.1,
        0.003,
        2,
        10.133,
        0.003,
        2,
        10.167,
        0.003,
        2,
        10.267,
        0.003,
        2,
        10.467,
        0.003,
        2,
        10.533,
        0.003,
        2,
        10.6,
        0.003,
        2,
        10.633,
        0.003,
        0,
        10.667,
        0.002,
        2,
        10.767,
        0.002,
        2,
        10.8,
        0.002,
        2,
        10.833,
        0.002,
        2,
        10.867,
        0.002,
        2,
        10.967,
        0.002,
        2,
        11,
        0.002,
        2,
        11.033,
        0.002,
        2,
        11.067,
        0.002,
        2,
        11.133,
        0.002,
        2,
        11.167,
        0.002,
        2,
        11.233,
        0.002,
        2,
        11.267,
        0.002,
        2,
        11.367,
        0.002,
        2,
        11.4,
        0.002,
        0,
        12.567,
        0.2,
        0,
        13.133,
        0.028,
        0,
        13.167,
        0.029,
        0,
        14.067,
        0
      ]
    },
    {
      "Target": "Parameter",
      "Id": "ParamOpaishakeY2",
      "Segments": [
        0,
        0,
        0,
        0.333,
        0.4,
        0,
        1.167,
        -0.6,
        0,
        1.733,
        0.2,
        0,
        2,
        -0.1,
        0,
        2.2,
        -0.003,
        0,
        2.633,
        -0.023,
        2,
        2.667,
        -0.023,
        0,
        2.933,
        -0.015,
        0,
        2.967,
        -0.016,
        2,
        3,
        -0.016,
        0,
        3.033,
        -0.017,
        2,
        3.067,
        -0.017,
        2,
        3.1,
        -0.017,
        0,
        3.133,
        -0.016,
        0,
        3.167,
        -0.017,
        0,
        3.567,
        -0.01,
        2,
        3.633,
        -0.01,
        0,
        3.967,
        0.037,
        0,
        4.233,
        0.018,
        0,
        4.5,
        0.024,
        0,
        4.533,
        0.023,
        2,
        4.567,
        0.023,
        2,
        4.733,
        0.023,
        2,
        4.767,
        0.023,
        2,
        4.8,
        0.023,
        2,
        4.833,
        0.023,
        2,
        4.867,
        0.023,
        0,
        4.9,
        0.022,
        2,
        4.933,
        0.022,
        2,
        4.967,
        0.022,
        2,
        5,
        0.022,
        2,
        5.033,
        0.022,
        2,
        5.067,
        0.022,
        0,
        5.633,
        0.018,
        0,
        5.7,
        0.022,
        2,
        5.733,
        0.022,
        0,
        6.3,
        -0.043,
        0,
        6.367,
        -0.041,
        2,
        6.4,
        -0.041,
        2,
        6.433,
        -0.041,
        2,
        6.467,
        -0.041,
        2,
        6.5,
        -0.041,
        2,
        6.533,
        -0.041,
        2,
        6.567,
        -0.041,
        0,
        7.067,
        0.009,
        0,
        7.333,
        -0.015,
        1,
        7.466,
        -0.015,
        7.6,
        -0.021,
        7.733,
        0,
        1,
        7.889,
        0.025,
        8.044,
        0.6,
        8.2,
        0.6,
        0,
        8.933,
        -0.5,
        0,
        9.533,
        0.3,
        0,
        9.767,
        -0.006,
        0,
        10.433,
        0.015,
        2,
        10.467,
        0.015,
        2,
        10.5,
        0.015,
        2,
        10.567,
        0.015,
        0,
        10.7,
        0.014,
        2,
        10.733,
        0.014,
        0,
        11.833,
        -0.067,
        2,
        11.867,
        -0.067,
        0,
        11.9,
        -0.068,
        0,
        11.933,
        -0.067,
        2,
        11.967,
        -0.067,
        0,
        13.2,
        0.057,
        2,
        13.233,
        0.057,
        0,
        13.3,
        0.058,
        0,
        14.067,
        0
      ]
    },
    {
      "Target": "Parameter",
      "Id": "ParamHairFront",
      "Segments": [
        0,
        -0.113,
        0,
        0.533,
        1,
        0,
        1.2,
        -1,
        0,
        1.867,
        0.3,
        1,
        2.067,
        0.3,
        2.267,
        0.221,
        2.467,
        0,
        1,
        2.745,
        -0.308,
        3.022,
        -0.5,
        3.3,
        -0.5,
        1,
        3.6,
        -0.5,
        3.9,
        0.071,
        4.2,
        0.6,
        1,
        4.411,
        0.972,
        4.622,
        1,
        4.833,
        1,
        1,
        5.044,
        1,
        5.256,
        0.77,
        5.467,
        0.6,
        1,
        5.645,
        0.457,
        5.822,
        0.482,
        6,
        0.3,
        1,
        6.289,
        0.004,
        6.578,
        -0.6,
        6.867,
        -0.6,
        1,
        7.178,
        -0.6,
        7.489,
        -0.228,
        7.8,
        0.5,
        1,
        7.944,
        0.838,
        8.089,
        1,
        8.233,
        1,
        0,
        8.9,
        -0.8,
        1,
        9.111,
        -0.8,
        9.322,
        -0.277,
        9.533,
        0,
        1,
        9.811,
        0.364,
        10.089,
        0.4,
        10.367,
        0.4,
        0,
        11.167,
        -0.4,
        0,
        11.833,
        0.5,
        0,
        12.733,
        -0.4,
        0,
        13.333,
        1,
        0,
        14.067,
        -0.113
      ]
    },
    {
      "Target": "Parameter",
      "Id": "ParamHaiFrontY",
      "Segments": [
        0,
        -0.086,
        0,
        0.833,
        1,
        0,
        1.5,
        -1,
        0,
        2.167,
        0.3,
        1,
        2.367,
        0.3,
        2.567,
        0.221,
        2.767,
        0,
        1,
        3.045,
        -0.308,
        3.322,
        -0.5,
        3.6,
        -0.5,
        1,
        3.9,
        -0.5,
        4.2,
        0.071,
        4.5,
        0.6,
        1,
        4.711,
        0.972,
        4.922,
        1,
        5.133,
        1,
        1,
        5.344,
        1,
        5.556,
        0.77,
        5.767,
        0.6,
        1,
        5.945,
        0.457,
        6.122,
        0.458,
        6.3,
        0.3,
        1,
        6.589,
        0.043,
        6.878,
        -0.3,
        7.167,
        -0.3,
        1,
        7.478,
        -0.3,
        7.789,
        -0.081,
        8.1,
        0.5,
        1,
        8.244,
        0.77,
        8.389,
        1,
        8.533,
        1,
        0,
        9.2,
        -0.8,
        1,
        9.411,
        -0.8,
        9.622,
        -0.328,
        9.833,
        0,
        1,
        10.111,
        0.431,
        10.389,
        0.5,
        10.667,
        0.5,
        0,
        11.467,
        -0.4,
        0,
        12.133,
        0.5,
        0,
        13.033,
        -0.4,
        0,
        13.633,
        1,
        0,
        14.067,
        -0.086
      ]
    },
    {
      "Target": "Parameter",
      "Id": "ParamHairFront2",
      "Segments": [
        0,
        0.161,
        0,
        0.5,
        1,
        0,
        1.167,
        -1,
        0,
        1.833,
        0.2,
        1,
        2.033,
        0.2,
        2.233,
        0.18,
        2.433,
        0,
        1,
        2.711,
        -0.25,
        2.989,
        -0.5,
        3.267,
        -0.5,
        1,
        3.567,
        -0.5,
        3.867,
        -0.071,
        4.167,
        0.5,
        1,
        4.378,
        0.902,
        4.589,
        1,
        4.8,
        1,
        1,
        5.011,
        1,
        5.222,
        0.635,
        5.433,
        0.5,
        1,
        5.611,
        0.386,
        5.789,
        0.427,
        5.967,
        0.3,
        1,
        6.256,
        0.094,
        6.544,
        -0.4,
        6.833,
        -0.4,
        1,
        7.144,
        -0.4,
        7.456,
        -0.207,
        7.767,
        0.4,
        1,
        7.911,
        0.682,
        8.056,
        1,
        8.2,
        1,
        0,
        8.867,
        -0.8,
        1,
        9.078,
        -0.8,
        9.289,
        -0.328,
        9.5,
        0,
        1,
        9.778,
        0.431,
        10.055,
        0.5,
        10.333,
        0.5,
        0,
        11.133,
        -0.4,
        0,
        11.8,
        0.5,
        0,
        12.7,
        -0.3,
        0,
        13.3,
        1,
        0,
        14.067,
        0.161
      ]
    },
    {
      "Target": "Parameter",
      "Id": "ParamHairSide",
      "Segments": [
        0,
        0.129,
        0,
        0.5,
        1,
        0,
        1.167,
        -1,
        0,
        1.833,
        0.3,
        1,
        2.033,
        0.3,
        2.233,
        0.243,
        2.433,
        0,
        1,
        2.711,
        -0.338,
        2.989,
        -0.6,
        3.267,
        -0.6,
        1,
        3.567,
        -0.6,
        3.867,
        -0.098,
        4.167,
        0.5,
        1,
        4.378,
        0.921,
        4.589,
        1,
        4.8,
        1,
        1,
        5.011,
        1,
        5.222,
        0.77,
        5.433,
        0.6,
        1,
        5.611,
        0.457,
        5.789,
        0.468,
        5.967,
        0.3,
        1,
        6.256,
        0.028,
        6.544,
        -0.4,
        6.833,
        -0.4,
        1,
        7.144,
        -0.4,
        7.456,
        -0.133,
        7.767,
        0.5,
        1,
        7.911,
        0.794,
        8.056,
        1,
        8.2,
        1,
        0,
        8.867,
        -0.8,
        1,
        9.078,
        -0.8,
        9.289,
        -0.22,
        9.5,
        0,
        1,
        9.778,
        0.289,
        10.055,
        0.3,
        10.333,
        0.3,
        0,
        11.133,
        -0.4,
        0,
        11.8,
        0.5,
        0,
        12.7,
        -0.4,
        0,
        13.3,
        1,
        0,
        14.067,
        0.129
      ]
    },
    {
      "Target": "Parameter",
      "Id": "ParamHairFrontY",
      "Segments": [
        0,
        -0.272,
        0,
        0.833,
        1,
        0,
        1.5,
        -1,
        0,
        2.167,
        0.3,
        1,
        2.367,
        0.3,
        2.567,
        0.243,
        2.767,
        0,
        1,
        3.045,
        -0.338,
        3.322,
        -0.6,
        3.6,
        -0.6,
        1,
        3.9,
        -0.6,
        4.2,
        0.052,
        4.5,
        0.6,
        1,
        4.711,
        0.986,
        4.922,
        1,
        5.133,
        1,
        1,
        5.344,
        1,
        5.556,
        0.728,
        5.767,
        0.6,
        1,
        5.945,
        0.492,
        6.122,
        0.535,
        6.3,
        0.4,
        1,
        6.589,
        0.18,
        6.878,
        -0.5,
        7.167,
        -0.5,
        1,
        7.478,
        -0.5,
        7.789,
        -0.182,
        8.1,
        0.5,
        1,
        8.244,
        0.817,
        8.389,
        1,
        8.533,
        1,
        0,
        9.2,
        -0.7,
        1,
        9.411,
        -0.7,
        9.622,
        -0.214,
        9.833,
        0,
        1,
        10.111,
        0.282,
        10.389,
        0.3,
        10.667,
        0.3,
        0,
        11.467,
        -0.4,
        0,
        12.133,
        0.5,
        0,
        13.033,
        -0.3,
        0,
        13.633,
        1,
        0,
        14.067,
        -0.272
      ]
    },
    {
      "Target": "Parameter",
      "Id": "ParamHairSide2",
      "Segments": [
        0,
        0.13,
        0,
        0.667,
        1,
        0,
        1.333,
        -1,
        0,
        2,
        0.3,
        1,
        2.2,
        0.3,
        2.4,
        0.243,
        2.6,
        0,
        1,
        2.878,
        -0.338,
        3.155,
        -0.6,
        3.433,
        -0.6,
        1,
        3.733,
        -0.6,
        4.033,
        0.052,
        4.333,
        0.6,
        1,
        4.544,
        0.986,
        4.756,
        1,
        4.967,
        1,
        1,
        5.178,
        1,
        5.389,
        0.77,
        5.6,
        0.6,
        1,
        5.778,
        0.457,
        5.955,
        0.482,
        6.133,
        0.3,
        1,
        6.422,
        0.004,
        6.711,
        -0.6,
        7,
        -0.6,
        1,
        7.311,
        -0.6,
        7.622,
        -0.318,
        7.933,
        0.4,
        1,
        8.078,
        0.733,
        8.222,
        1,
        8.367,
        1,
        0,
        9.033,
        -0.8,
        1,
        9.244,
        -0.8,
        9.456,
        -0.22,
        9.667,
        0,
        1,
        9.945,
        0.289,
        10.222,
        0.3,
        10.5,
        0.3,
        0,
        11.3,
        -0.4,
        0,
        11.967,
        0.5,
        0,
        12.867,
        -0.2,
        0,
        13.467,
        1,
        0,
        14.067,
        0.13
      ]
    },
    {
      "Target": "Parameter",
      "Id": "ParamHairSide2y",
      "Segments": [
        0,
        -0.23,
        0,
        1,
        1,
        0,
        1.667,
        -1,
        0,
        2.333,
        0.3,
        1,
        2.533,
        0.3,
        2.733,
        0.243,
        2.933,
        0,
        1,
        3.211,
        -0.338,
        3.489,
        -0.6,
        3.767,
        -0.6,
        1,
        4.067,
        -0.6,
        4.367,
        0.052,
        4.667,
        0.6,
        1,
        4.878,
        0.986,
        5.089,
        1,
        5.3,
        1,
        1,
        5.511,
        1,
        5.722,
        0.728,
        5.933,
        0.6,
        1,
        6.111,
        0.492,
        6.289,
        0.541,
        6.467,
        0.4,
        1,
        6.756,
        0.171,
        7.044,
        -0.7,
        7.333,
        -0.7,
        1,
        7.644,
        -0.7,
        7.956,
        -0.37,
        8.267,
        0.4,
        1,
        8.411,
        0.757,
        8.556,
        1,
        8.7,
        1,
        0,
        9.367,
        -0.8,
        1,
        9.578,
        -0.8,
        9.789,
        -0.22,
        10,
        0,
        1,
        10.278,
        0.289,
        10.555,
        0.3,
        10.833,
        0.3,
        0,
        11.633,
        -0.4,
        0,
        12.3,
        0.5,
        0,
        13.2,
        -0.2,
        0,
        13.8,
        1,
        0,
        14.067,
        -0.23
      ]
    },
    {
      "Target": "Parameter",
      "Id": "ParamHairBack",
      "Segments": [
        0,
        0.157,
        0,
        0.5,
        1,
        0,
        1.167,
        -1,
        0,
        1.833,
        0.3,
        1,
        2.055,
        0.3,
        2.278,
        0.192,
        2.5,
        -0.2,
        1,
        2.756,
        -0.651,
        3.011,
        -1,
        3.267,
        -1,
        1,
        3.556,
        -1,
        3.844,
        0.287,
        4.133,
        0.7,
        1,
        4.378,
        1,
        4.622,
        1,
        4.867,
        1,
        1,
        5.234,
        1,
        5.6,
        0.965,
        5.967,
        0.4,
        1,
        6.256,
        -0.045,
        6.544,
        -1,
        6.833,
        -1,
        1,
        7.133,
        -1,
        7.433,
        -0.417,
        7.733,
        0.4,
        1,
        7.911,
        0.884,
        8.089,
        1,
        8.267,
        1,
        0,
        8.9,
        -1,
        1,
        9.122,
        -1,
        9.345,
        -0.072,
        9.567,
        0.1,
        1,
        9.845,
        0.315,
        10.122,
        0.3,
        10.4,
        0.3,
        0,
        11.3,
        -0.4,
        0,
        11.867,
        0.4,
        0,
        12.6,
        -0.2,
        0,
        13.4,
        1,
        0,
        14.067,
        0.157
      ]
    },
    {
      "Target": "Parameter",
      "Id": "ParamHairBackY",
      "Segments": [
        0,
        0,
        0,
        0.833,
        1,
        0,
        1.5,
        -1,
        0,
        2.167,
        0.3,
        1,
        2.389,
        0.3,
        2.611,
        0.192,
        2.833,
        -0.2,
        1,
        3.089,
        -0.651,
        3.344,
        -1,
        3.6,
        -1,
        1,
        3.889,
        -1,
        4.178,
        0.091,
        4.467,
        0.6,
        1,
        4.711,
        1,
        4.956,
        1,
        5.2,
        1,
        1,
        5.567,
        1,
        5.933,
        0.925,
        6.3,
        0.3,
        1,
        6.589,
        -0.193,
        6.878,
        -1,
        7.167,
        -1,
        1,
        7.467,
        -1,
        7.767,
        -0.417,
        8.067,
        0.4,
        1,
        8.245,
        0.884,
        8.422,
        1,
        8.6,
        1,
        0,
        9.233,
        -1,
        1,
        9.455,
        -1,
        9.678,
        -0.072,
        9.9,
        0.1,
        1,
        10.178,
        0.315,
        10.455,
        0.3,
        10.733,
        0.3,
        0,
        11.633,
        -0.4,
        0,
        12.2,
        0.4,
        0,
        12.933,
        -0.3,
        0,
        13.733,
        1,
        0,
        14.067,
        0
      ]
    },
    {
      "Target": "Parameter",
      "Id": "ParamHairBack2",
      "Segments": [
        0,
        -0.029,
        0,
        0.367,
        1,
        0,
        1.033,
        -1,
        0,
        1.7,
        0.3,
        1,
        1.922,
        0.3,
        2.145,
        0.261,
        2.367,
        -0.1,
        1,
        2.622,
        -0.515,
        2.878,
        -1,
        3.133,
        -1,
        1,
        3.422,
        -1,
        3.711,
        0.287,
        4,
        0.7,
        1,
        4.244,
        1,
        4.489,
        1,
        4.733,
        1,
        1,
        5.1,
        1,
        5.466,
        0.925,
        5.833,
        0.3,
        1,
        6.122,
        -0.193,
        6.411,
        -1,
        6.7,
        -1,
        1,
        7,
        -1,
        7.3,
        -0.417,
        7.6,
        0.4,
        1,
        7.778,
        0.884,
        7.955,
        1,
        8.133,
        1,
        0,
        8.767,
        -1,
        1,
        8.989,
        -1,
        9.211,
        -0.242,
        9.433,
        0,
        1,
        9.711,
        0.302,
        9.989,
        0.3,
        10.267,
        0.3,
        0,
        11.167,
        -0.5,
        0,
        11.733,
        0.5,
        0,
        12.467,
        -0.3,
        0,
        13.267,
        1,
        0,
        14.067,
        -0.029
      ]
    },
    {
      "Target": "Parameter",
      "Id": "ParamHairBack2Y",
      "Segments": [
        0,
        0,
        0,
        0.633,
        1,
        0,
        1.3,
        -1,
        0,
        1.967,
        0.3,
        1,
        2.189,
        0.3,
        2.411,
        0.261,
        2.633,
        -0.1,
        1,
        2.889,
        -0.515,
        3.144,
        -1,
        3.4,
        -1,
        1,
        3.689,
        -1,
        3.978,
        0.091,
        4.267,
        0.6,
        1,
        4.511,
        1,
        4.756,
        1,
        5,
        1,
        1,
        5.367,
        1,
        5.733,
        0.925,
        6.1,
        0.3,
        1,
        6.389,
        -0.193,
        6.678,
        -1,
        6.967,
        -1,
        1,
        7.267,
        -1,
        7.567,
        -0.535,
        7.867,
        0.3,
        1,
        8.045,
        0.795,
        8.222,
        1,
        8.4,
        1,
        0,
        9.033,
        -1,
        1,
        9.255,
        -1,
        9.478,
        -0.072,
        9.7,
        0.1,
        1,
        9.978,
        0.315,
        10.255,
        0.3,
        10.533,
        0.3,
        0,
        11.433,
        -0.5,
        0,
        12,
        0.4,
        0,
        12.733,
        -0.4,
        0,
        13.533,
        1,
        0,
        14.067,
        0
      ]
    },
    {
      "Target": "Parameter",
      "Id": "ParamClothes",
      "Segments": [
        0,
        0.07,
        0,
        0.533,
        0.3,
        0,
        1,
        -0.4,
        1,
        1.667,
        -0.4,
        2.333,
        -0.394,
        3,
        -0.3,
        1,
        3.3,
        -0.258,
        3.6,
        0.4,
        3.9,
        0.4,
        1,
        4.078,
        0.4,
        4.255,
        0.102,
        4.433,
        0.1,
        1,
        4.9,
        0.095,
        5.366,
        0.096,
        5.833,
        0.09,
        1,
        6.144,
        0.086,
        6.456,
        -0.3,
        6.767,
        -0.3,
        0,
        7.2,
        0.3,
        1,
        7.433,
        0.3,
        7.667,
        0.302,
        7.9,
        0.2,
        1,
        8.044,
        0.137,
        8.189,
        -0.5,
        8.333,
        -0.5,
        2,
        11,
        -0.5,
        0,
        11.7,
        -0.7,
        0,
        12.467,
        1,
        0,
        14.067,
        0.07
      ]
    },
    {
      "Target": "Parameter",
      "Id": "ParamClothesY",
      "Segments": [
        0,
        0.07,
        0,
        0.533,
        0.3,
        0,
        1,
        -0.5,
        1,
        1.667,
        -0.5,
        2.333,
        -0.494,
        3,
        -0.4,
        1,
        3.3,
        -0.358,
        3.6,
        0.3,
        3.9,
        0.3,
        0,
        4.433,
        0,
        0,
        5.833,
        0.006,
        0,
        6.767,
        -0.4,
        0,
        7.2,
        0.3,
        1,
        7.433,
        0.3,
        7.667,
        0.304,
        7.9,
        0.2,
        1,
        8.044,
        0.136,
        8.189,
        -0.7,
        8.333,
        -0.7,
        2,
        11,
        -0.7,
        1,
        11.233,
        -0.7,
        11.467,
        -0.723,
        11.7,
        -0.6,
        1,
        11.956,
        -0.465,
        12.211,
        0.3,
        12.467,
        0.3,
        0,
        14.067,
        0.07
      ]
    },
    {
      "Target": "Parameter",
      "Id": "ParamClothes2",
      "Segments": [
        0,
        0,
        0,
        0.667,
        -0.7,
        0,
        2.333,
        0.7,
        0,
        7.233,
        0.436,
        1,
        7.533,
        0.436,
        7.833,
        0.493,
        8.133,
        0.6,
        1,
        8.889,
        0.869,
        9.644,
        1,
        10.4,
        1,
        1,
        11.311,
        1,
        12.222,
        0.956,
        13.133,
        0.7,
        1,
        13.444,
        0.613,
        13.756,
        0,
        14.067,
        0
      ]
    },
    {
      "Target": "Parameter",
      "Id": "ParamClothes2Y",
      "Segments": [
        0,
        0,
        0,
        0.667,
        -0.3,
        0,
        2.333,
        0.6,
        0,
        7.3,
        0.369,
        0,
        8.133,
        0.8,
        1,
        8.889,
        0.8,
        9.644,
        0.76,
        10.4,
        0.7,
        1,
        11.311,
        0.628,
        12.222,
        0.587,
        13.133,
        0.5,
        1,
        13.444,
        0.47,
        13.756,
        0,
        14.067,
        0
      ]
    },
    {
      "Target": "Parameter",
      "Id": "ParamSkirt",
      "Segments": [
        0,
        0,
        0,
        0.967,
        0.3,
        0,
        1.733,
        -0.7,
        1,
        2.033,
        -0.7,
        2.333,
        -0.648,
        2.633,
        -0.4,
        1,
        3.111,
        -0.004,
        3.589,
        0.3,
        4.067,
        0.3,
        0,
        4.967,
        -0.1,
        0,
        6.167,
        0.1,
        0,
        7.367,
        0,
        2,
        7.9,
        0,
        0,
        8.6,
        -1,
        1,
        9.278,
        -1,
        9.955,
        -0.993,
        10.633,
        -0.9,
        1,
        11,
        -0.85,
        11.366,
        -0.633,
        11.733,
        -0.339,
        1,
        12.089,
        -0.054,
        12.444,
        0.7,
        12.8,
        0.7,
        0,
        14.067,
        0
      ]
    },
    {
      "Target": "Parameter",
      "Id": "ParamSkirtY",
      "Segments": [
        0,
        0,
        2,
        7.267,
        0,
        0,
        8.067,
        0.3,
        0,
        9.033,
        -0.7,
        0,
        14.067,
        0
      ]
    },
    {
      "Target": "Parameter",
      "Id": "ParamSkirt2",
      "Segments": [
        0,
        0,
        0,
        1.767,
        0.6,
        0,
        4.067,
        -0.4,
        0,
        6.567,
        0.3,
        0,
        9.567,
        -0.2,
        0,
        11.767,
        0.3,
        0,
        14.067,
        0
      ]
    },
    {
      "Target": "Parameter",
      "Id": "ParamAngleX",
      "Segments": [
        0,
        -9.537,
        0,
        1.067,
        30,
        2,
        2.1,
        30,
        1,
        2.422,
        30,
        2.745,
        14.022,
        3.067,
        11,
        1,
        4.034,
        1.933,
        5,
        0,
        5.967,
        0,
        0,
        6.933,
        30,
        2,
        8.133,
        30,
        0,
        9.233,
        -30,
        2,
        10.367,
        -30,
        0,
        11.267,
        30,
        0,
        11.867,
        0,
        0,
        12.467,
        30,
        1,
        12.711,
        30,
        12.956,
        7.733,
        13.2,
        0,
        1,
        13.489,
        -9.139,
        13.778,
        -9.537,
        14.067,
        -9.537
      ]
    },
    {
      "Target": "Parameter",
      "Id": "ParamAngleY",
      "Segments": [
        0,
        -24.962,
        0,
        0.6,
        0,
        1,
        1.1,
        0,
        1.6,
        -4.585,
        2.1,
        -16,
        1,
        2.289,
        -20.312,
        2.478,
        -24,
        2.667,
        -24,
        1,
        2.822,
        -24,
        2.978,
        -23.924,
        3.133,
        -17.629,
        1,
        3.278,
        -11.783,
        3.422,
        6,
        3.567,
        6,
        0,
        3.933,
        0,
        0,
        4.7,
        30,
        0,
        5.2,
        0,
        1,
        5.4,
        0,
        5.6,
        10.144,
        5.8,
        14,
        1,
        6.444,
        26.425,
        7.089,
        30,
        7.733,
        30,
        0,
        14.067,
        -24.962
      ]
    },
    {
      "Target": "Parameter",
      "Id": "ParamAngleZ",
      "Segments": [
        0,
        13.351,
        0,
        0.767,
        27,
        0,
        1.9,
        17,
        0,
        6.9,
        19,
        0,
        7.7,
        11,
        0,
        8.133,
        18,
        0,
        9.033,
        3,
        0,
        12.333,
        30,
        0,
        14.067,
        13.351
      ]
    },
    {
      "Target": "Parameter",
      "Id": "ParamBodyAngleX",
      "Segments": [
        0,
        0,
        2,
        1.033,
        0,
        0,
        2.033,
        4,
        1,
        2.211,
        4,
        2.389,
        4.056,
        2.567,
        3.928,
        1,
        2.878,
        3.705,
        3.189,
        -3,
        3.5,
        -3,
        1,
        4.4,
        -3,
        5.3,
        -2.478,
        6.2,
        0,
        1,
        6.444,
        0.673,
        6.689,
        10,
        6.933,
        10,
        2,
        7.733,
        10,
        0,
        9.733,
        8,
        0,
        11.4,
        10,
        0,
        14.067,
        0
      ]
    },
    {
      "Target": "Parameter",
      "Id": "ParamBodyAngleY",
      "Segments": [
        0,
        0,
        0,
        0.567,
        10,
        0,
        1.167,
        -3,
        1,
        1.622,
        -3,
        2.078,
        -2.599,
        2.533,
        -0.482,
        1,
        2.833,
        0.912,
        3.133,
        3,
        3.433,
        3,
        0,
        4.333,
        -5,
        2,
        5.9,
        -5,
        1,
        6.278,
        -5,
        6.655,
        -4,
        7.033,
        1,
        1,
        7.344,
        5.118,
        7.656,
        10,
        7.967,
        10,
        0,
        8.6,
        -5,
        0,
        11.5,
        1,
        0,
        14.067,
        0
      ]
    },
    {
      "Target": "Parameter",
      "Id": "ParamBodyAngleZ",
      "Segments": [
        0,
        0,
        1,
        0.289,
        0,
        0.578,
        0.741,
        0.867,
        4.006,
        1,
        1.134,
        7.02,
        1.4,
        10,
        1.667,
        10,
        1,
        1.967,
        10,
        2.267,
        10,
        2.567,
        9.91,
        1,
        2.956,
        9.739,
        3.344,
        3.595,
        3.733,
        3,
        1,
        4.833,
        1.318,
        5.933,
        1,
        7.033,
        1,
        2,
        7.967,
        1,
        0,
        8.6,
        0,
        0,
        9.467,
        9,
        1,
        10.145,
        9,
        10.822,
        1.877,
        11.5,
        1,
        1,
        12.356,
        -0.107,
        13.211,
        0,
        14.067,
        0
      ]
    },
    {
      "Target": "Parameter",
      "Id": "ParamNY",
      "Segments": [
        0,
        0,
        0,
        0.867,
        -10,
        1,
        1.134,
        -10,
        1.4,
        -7.513,
        1.667,
        -7,
        1,
        1.956,
        -6.444,
        2.244,
        -6.775,
        2.533,
        -6.01,
        1,
        2.989,
        -4.803,
        3.444,
        6,
        3.9,
        6,
        1,
        4.567,
        6,
        5.233,
        4.654,
        5.9,
        3,
        1,
        6.256,
        2.118,
        6.611,
        2.001,
        6.967,
        2.001,
        0,
        7.8,
        3,
        0,
        8.467,
        -4,
        1,
        8.756,
        -4,
        9.044,
        -0.274,
        9.333,
        0,
        1,
        10.044,
        0.675,
        10.756,
        0.74,
        11.467,
        1.485,
        1,
        11.856,
        1.892,
        12.244,
        10,
        12.633,
        10,
        0,
        14.067,
        0
      ]
    },
    {
      "Target": "Parameter",
      "Id": "ParamBreath",
      "Segments": [
        0,
        0,
        0,
        3.367,
        1,
        0,
        7,
        0,
        0,
        10.5,
        1,
        0,
        14.067,
        0
      ]
    },
    {
      "Target": "Parameter",
      "Id": "ParamEyeLSmile",
      "Segments": [
        0,
        1,
        0,
        14.07,
        1
      ]
    },
    {
      "Target": "Parameter",
      "Id": "ParamEyeBallY",
      "Segments": [
        0,
        0,
        0,
        14.07,
        0
      ]
    },
    {
      "Target": "Parameter",
      "Id": "ParamEyesZoom",
      "Segments": [
        0,
        0,
        0,
        14.07,
        0
      ]
    },
    {
      "Target": "Parameter",
      "Id": "ParamMouthX",
      "Segments": [
        0,
        0,
        0,
        14.07,
        0
      ]
    },
    {
      "Target": "Parameter",
      "Id": "ParamArmLMoveX",
      "Segments": [
        0,
        0,
        0,
        14.07,
        0
      ]
    },
    {
      "Target": "Parameter",
      "Id": "ParamArmLMoveY",
      "Segments": [
        0,
        0,
        0,
        14.07,
        0
      ]
    },
    {
      "Target": "Parameter",
      "Id": "ParamArmLY",
      "Segments": [
        0,
        0,
        0,
        14.07,
        0
      ]
    },
    {
      "Target": "Parameter",
      "Id": "ParamZMZ",
      "Segments": [
        0,
        0,
        0,
        14.07,
        0
      ]
    },
    {
      "Target": "Parameter",
      "Id": "ParamGOU",
      "Segments": [
        0,
        0,
        0,
        14.07,
        0
      ]
    },
    {
      "Target": "Parameter",
      "Id": "ParamArmRMoveX",
      "Segments": [
        0,
        0,
        0,
        14.07,
        0
      ]
    },
    {
      "Target": "Parameter",
      "Id": "ParamArmRMoveY",
      "Segments": [
        0,
        0,
        0,
        14.07,
        0
      ]
    },
    {
      "Target": "Parameter",
      "Id": "ParamSX",
      "Segments": [
        0,
        0,
        0,
        14.07,
        0
      ]
    },
    {
      "Target": "Parameter",
      "Id": "ParamLegLMoveX",
      "Segments": [
        0,
        0,
        0,
        14.07,
        0
      ]
    },
    {
      "Target": "Parameter",
      "Id": "ParamLegLMoveY",
      "Segments": [
        0,
        0,
        0,
        14.07,
        0
      ]
    },
    {
      "Target": "Parameter",
      "Id": "ParamLegL1Y",
      "Segments": [
        0,
        0,
        0,
        14.07,
        0
      ]
    },
    {
      "Target": "Parameter",
      "Id": "ParamLegRMoveX",
      "Segments": [
        0,
        0,
        0,
        14.07,
        0
      ]
    },
    {
      "Target": "Parameter",
      "Id": "ParamLegRMoveY",
      "Segments": [
        0,
        0,
        0,
        14.07,
        0
      ]
    },
    {
      "Target": "Parameter",
      "Id": "ParamLegR1Y",
      "Segments": [
        0,
        0,
        0,
        14.07,
        0
      ]
    },
    {
      "Target": "Parameter",
      "Id": "ParamBACKGROUND",
      "Segments": [
        0,
        0,
        0,
        14.07,
        0
      ]
    },
    {
      "Target": "Parameter",
      "Id": "ParamBlack0",
      "Segments": [
        0,
        0,
        0,
        14.07,
        0
      ]
    },
    {
      "Target": "Parameter",
      "Id": "ParamBLACKSHOW",
      "Segments": [
        0,
        0,
        0,
        14.07,
        0
      ]
    },
    {
      "Target": "Parameter",
      "Id": "ParamCamX",
      "Segments": [
        0,
        0,
        0,
        14.07,
        0
      ]
    },
    {
      "Target": "Parameter",
      "Id": "ParamCamY",
      "Segments": [
        0,
        0,
        0,
        14.07,
        0
      ]
    },
    {
      "Target": "Parameter",
      "Id": "ParamCamZoom",
      "Segments": [
        0,
        0,
        0,
        14.07,
        0
      ]
    },
    {
      "Target": "Parameter",
      "Id": "ParamTIOP",
      "Segments": [
        0,
        0,
        0,
        14.07,
        0
      ]
    },
    {
      "Target": "Parameter",
      "Id": "ParamTSD",
      "Segments": [
        0,
        0,
        0,
        14.07,
        0
      ]
    },
    {
      "Target": "Parameter",
      "Id": "ParamQSP",
      "Segments": [
        0,
        0,
        0,
        14.07,
        0
      ]
    },
    {
      "Target": "Parameter",
      "Id": "ParamDS",
      "Segments": [
        0,
        0,
        0,
        14.07,
        0
      ]
    },
    {
      "Target": "Parameter",
      "Id": "ParamGAI",
      "Segments": [
        0,
        -0.1,
        0,
        14.07,
        -0.1
      ]
    },
    {
      "Target": "Parameter",
      "Id": "ParamSSD",
      "Segments": [
        0,
        0,
        0,
        14.07,
        0
      ]
    },
    {
      "Target": "Parameter",
      "Id": "ParamGOUZ",
      "Segments": [
        0,
        0,
        0,
        14.07,
        0
      ]
    },
    {
      "Target": "Parameter",
      "Id": "ParamZZY",
      "Segments": [
        0,
        0,
        0,
        14.07,
        0
      ]
    },
    {
      "Target": "Parameter",
      "Id": "ParamRYXN",
      "Segments": [
        0,
        0,
        0,
        14.07,
        0
      ]
    },
    {
      "Target": "Parameter",
      "Id": "ParamRYYN",
      "Segments": [
        0,
        0,
        0,
        14.07,
        0
      ]
    },
    {
      "Target": "Parameter",
      "Id": "ParamHairFront2Y",
      "Segments": [
        0,
        0,
        0,
        14.07,
        0
      ]
    },
    {
      "Target": "Parameter",
      "Id": "ParamHairFront3",
      "Segments": [
        0,
        0,
        0,
        14.07,
        0
      ]
    },
    {
      "Target": "Parameter",
      "Id": "ParamHairFront3Y",
      "Segments": [
        0,
        0,
        0,
        14.07,
        0
      ]
    },
    {
      "Target": "Parameter",
      "Id": "ParamSkirt2Y",
      "Segments": [
        0,
        0,
        0,
        14.07,
        0
      ]
    },
    {
      "Target": "Parameter",
      "Id": "ParamSleeveL",
      "Segments": [
        0,
        0,
        0,
        14.07,
        0
      ]
    },
    {
      "Target": "Parameter",
      "Id": "ParamSleeveY",
      "Segments": [
        0,
        0,
        0,
        14.07,
        0
      ]
    },
    {
      "Target": "Parameter",
      "Id": "ParamSleeveR",
      "Segments": [
        0,
        0,
        0,
        14.07,
        0
      ]
    },
    {
      "Target": "Parameter",
      "Id": "ParamSleeveRY",
      "Segments": [
        0,
        0,
        0,
        14.07,
        0
      ]
    },
    {
      "Target": "Parameter",
      "Id": "ParamMisk",
      "Segments": [
        0,
        0,
        0,
        14.07,
        0
      ]
    },
    {
      "Target": "Parameter",
      "Id": "ParamCheek",
      "Segments": [
        0,
        0,
        0,
        14.07,
        0
      ]
    },
    {
      "Target": "Parameter",
      "Id": "ParamHipX",
      "Segments": [
        0,
        0,
        0,
        14.07,
        0
      ]
    },
    {
      "Target": "Parameter",
      "Id": "ParamHipY",
      "Segments": [
        0,
        0,
        0,
        14.07,
        0
      ]
    },
    {
      "Target": "Parameter",
      "Id": "ParamWX",
      "Segments": [
        0,
        0,
        0,
        14.07,
        0
      ]
    },
    {
      "Target": "Parameter",
      "Id": "ParamWY",
      "Segments": [
        0,
        0,
        0,
        14.07,
        0
      ]
    },
    {
      "Target": "Parameter",
      "Id": "ParamWZoom",
      "Segments": [
        0,
        0,
        0,
        14.07,
        0
      ]
    },
    {
      "Target": "Parameter",
      "Id": "ParamLIGHT",
      "Segments": [
        0,
        -0.966,
        0,
        14.07,
        -0.966
      ]
    },
    {
      "Target": "Parameter",
      "Id": "ParamFLAGX",
      "Segments": [
        0,
        0.966,
        0,
        14.07,
        0.966
      ]
    },
    {
      "Target": "Parameter",
      "Id": "ParamFLAGY",
      "Segments": [
        0,
        0.957,
        0,
        14.07,
        0.957
      ]
    },
    {
      "Target": "Parameter",
      "Id": "ParamBALL2",
      "Segments": [
        0,
        0,
        0,
        14.07,
        0
      ]
    },
    {
      "Target": "Parameter",
      "Id": "ParamLightShow",
      "Segments": [
        0,
        0.037,
        0,
        14.07,
        0.037
      ]
    },
    {
      "Target": "Parameter",
      "Id": "ParamBirdX",
      "Segments": [
        0,
        -4,
        0,
        14.07,
        -4
      ]
    },
    {
      "Target": "Parameter",
      "Id": "ParamZB2",
      "Segments": [
        0,
        0.752,
        0,
        14.07,
        0.752
      ]
    },
    {
      "Target": "Parameter",
      "Id": "ParamBQL2",
      "Segments": [
        0,
        0.082,
        0,
        14.07,
        0.082
      ]
    },
    {
      "Target": "Parameter",
      "Id": "ParamBirdfly",
      "Segments": [
        0,
        0.021,
        0,
        14.07,
        0.021
      ]
    },
    {
      "Target": "Parameter",
      "Id": "ParamWaveY",
      "Segments": [
        0,
        0,
        0,
        14.07,
        0
      ]
    },
    {
      "Target": "Parameter",
      "Id": "ParamBY",
      "Segments": [
        0,
        0.281,
        0,
        14.07,
        0.281
      ]
    },
    {
      "Target": "Parameter",
      "Id": "Paramniaoz",
      "Segments": [
        0,
        0,
        0,
        14.07,
        0
      ]
    },
    {
      "Target": "Parameter",
      "Id": "ParamYYQ",
      "Segments": [
        0,
        0,
        0,
        14.07,
        0
      ]
    },
    {
      "Target": "Parameter",
      "Id": "ParamSTAR",
      "Segments": [
        0,
        0.983,
        0,
        14.07,
        0.983
      ]
    },
    {
      "Target": "Parameter",
      "Id": "ParamXXXS",
      "Segments": [
        0,
        0.017,
        0,
        14.07,
        0.017
      ]
    },
    {
      "Target": "Parameter",
      "Id": "ParamWAN",
      "Segments": [
        0,
        -9.573,
        0,
        14.07,
        -9.573
      ]
    },
    {
      "Target": "Parameter",
      "Id": "ParamNIAO",
      "Segments": [
        0,
        0,
        0,
        14.07,
        0
      ]
    },
    {
      "Target": "Parameter",
      "Id": "ParamCB",
      "Segments": [
        0,
        0.3,
        0,
        14.07,
        0.3
      ]
    },
    {
      "Target": "Parameter",
      "Id": "Paramnf",
      "Segments": [
        0,
        0.017,
        0,
        14.07,
        0.017
      ]
    }
  ],
  "UserData": [
    {
      "Time": 0.0,
      "Value": ""
    }
  ]
}